pdfcutter/__init__.py
pdfcutter/debug.py
pdfcutter/pdfcutter.py
pdfcutter/utils.py
pdfcutter-0.0.1.dist-info/METADATA
pdfcutter-0.0.1.dist-info/RECORD
pdfcutter-0.0.1.dist-info/WHEEL
pdfcutter-0.0.1.dist-info/top_level.txt
